pypergraph/__about__.py
pypergraph/__init__.py
pypergraph/account/__init__.py
pypergraph/account/dag_account.py
pypergraph/account/metagraph_client.py
pypergraph/account/monitor.py
pypergraph/account/utils.py
pypergraph/account/models/key_trio.py
pypergraph/account/tests/conftest.py
pypergraph/account/tests/secret.py
pypergraph/account/tests/test_account.py
pypergraph/core/__init__.py
pypergraph/core/constants.py
pypergraph/core/exceptions.py
pypergraph/core/cross_platform/__init__.py
pypergraph/core/cross_platform/rest_api_client.py
pypergraph/core/cross_platform/state_storage_db.py
pypergraph/core/cross_platform/di/__init__.py
pypergraph/core/cross_platform/di/json_storage.py
pypergraph/core/cross_platform/di/rest_client.py
pypergraph/keyring/__init__.py
pypergraph/keyring/encryptor.py
pypergraph/keyring/manager.py
pypergraph/keyring/accounts/__init__.py
pypergraph/keyring/accounts/asset_library.py
pypergraph/keyring/accounts/dag_account.py
pypergraph/keyring/accounts/dag_asset_library.py
pypergraph/keyring/accounts/ecdsa_account.py
pypergraph/keyring/accounts/eth_account.py
pypergraph/keyring/accounts/eth_asset_library.py
pypergraph/keyring/bip_helpers/__init__.py
pypergraph/keyring/bip_helpers/bip32_helper.py
pypergraph/keyring/bip_helpers/bip39_helper.py
pypergraph/keyring/keyrings/__init__.py
pypergraph/keyring/keyrings/hd_keyring.py
pypergraph/keyring/keyrings/registry.py
pypergraph/keyring/keyrings/simple_keyring.py
pypergraph/keyring/models/kcs.py
pypergraph/keyring/storage/__init__.py
pypergraph/keyring/storage/observable_store.py
pypergraph/keyring/storage/system_keyring_storage.py
pypergraph/keyring/tests/__init__.py
pypergraph/keyring/tests/monitor.py
pypergraph/keyring/tests/secret.py
pypergraph/keyring/tests/test_account.py
pypergraph/keyring/tests/test_asset_library.py
pypergraph/keyring/tests/test_async_aesgsm_encryptor.py
pypergraph/keyring/tests/test_keyring.py
pypergraph/keyring/wallets/__init__.py
pypergraph_dag-0.2.12.dist-info/METADATA
pypergraph_dag-0.2.12.dist-info/WHEEL
pypergraph_dag-0.2.12.dist-info/licenses/LICENSE
pypergraph_dag-0.2.12.dist-info/RECORD
