Metadata-Version: 2.4
Name: pypergraph-dag
Version: 0.2.12
Summary: The Pypergraph package provides secure wallet functionality in Python and convenient wrappers for interacting with Constellation Network APIs, inspired by the TypeScript library DAG4.js created by Stardust Collective.
Project-URL: Homepage, https://mringdal.com
Project-URL: Repository, https://github.com/buzzgreyday/pypergraph.git
Project-URL: Bug Tracker, https://github.com/buzzgreyday/pypergraph/issues
Author-email: Michael Brummer Ringdal <micbr@protonmail.com>
Maintainer-email: Michael Brummer Ringdal <micbr@pm.me>
License: MIT License
License-File: LICENSE
Keywords: collective,constellation,constellationnetwork,crypto,cryptocurrency,cryptography,dag,dag4,dag4.js,finance,hypergraph,metagraph,stardust,wallet
Classifier: Development Status :: 4 - Beta
Classifier: Intended Audience :: Developers
Classifier: Programming Language :: Python
Classifier: Topic :: Software Development :: Build Tools
Requires-Python: >=3.9
Requires-Dist: aiofiles~=24.1.0
Requires-Dist: argon2-cffi~=23.1.0
Requires-Dist: base58~=2.1.1
Requires-Dist: bip32utils~=0.3.post4
Requires-Dist: brotlipy~=0.7.0
Requires-Dist: cryptography~=44.0.1
Requires-Dist: eth-hash[pycryptodome]~=0.7.1
Requires-Dist: eth-keyfile~=0.8.1
Requires-Dist: eth-keys~=0.6.1
Requires-Dist: eth-utils~=5.2.0
Requires-Dist: httpx~=0.28.1
Requires-Dist: mnemonic~=0.21
Requires-Dist: prometheus-client~=0.21.1
Requires-Dist: pydantic~=2.10.6
Requires-Dist: rx~=3.2.0
